kollektor/__init__.py
kollektor/classes.py
kollektor-1.0.0.dist-info/LICENSE
kollektor-1.0.0.dist-info/METADATA
kollektor-1.0.0.dist-info/WHEEL
kollektor-1.0.0.dist-info/top_level.txt
kollektor-1.0.0.dist-info/RECORD
