Metadata-Version: 2.1
Name: kollektor
Version: 1.0.0
Summary: 📦 Collection utility for Python.
Home-page: https://github.com/kremayard/kollektor/
Author: kremayard
Author-email: 
License: MIT
Project-URL: Bug Tracker, https://github.com/kremayard/kollektor/issues
Keywords: python,collector,krema,collection
Platform: UNKNOWN
Classifier: Development Status :: 5 - Production/Stable
Classifier: Intended Audience :: Developers
Classifier: Operating System :: OS Independent
Classifier: License :: OSI Approved :: MIT License
Classifier: Programming Language :: Python :: 3
Requires-Python: >=3.6.0
